{"global":{"total":29,"age":{"min":46,"max":74,"median":52.0},"gender":{"male":15,"female":14},"political_leaning":{"Center-left (social democrat)":3,"Center (liberal)":1,"Conservative":5,"Other":3,"Left wing":1},"profession_category":{"Civil servant":2,"Other":4,"Teacher":1,"Private sector professional":4,"Journalist, public relations":1},"age_range":{"40-50":3,"over-70":1,"50-60":3}},"assigned":{"total":0,"age":{"min":null,"max":null,"median":null},"gender":{},"political_leaning":{},"profession_category":{},"age_range":{}}}